{
  "type": "Collection",
  "id": "GLOBAL_LAND_COVER",
  "stac_version": "1.0.0",
  "description": "Global Land Cover products at 100 m resolution are delivered annually by the \n[global component of the Copernicus Land Service](https://land.copernicus.eu/global/products/lc). \nThe most recent collection 3 (version 3.0.1) of 100 m Land Cover products for the years 2015 - 2019 were generated from \nthe PROBA-V 100 m and 300 m satellite observations and several other ancillary datasets with global coverage. \nThese Land Cover products provide a main discrete land cover classification map according to UN-FAO Land Cover Classification System [LCCS](https://land.copernicus.eu/global/products/lc). \nAdditional continuous fractional layers for all basic land cover classes which give the percentage of\na 100 m pixel that is filled with a specific land cover class, are also included in the Land Cover products to\nprovide more detailed information on each land cover class.\n",
  "links": [],
  "title": "Global Land Cover",
  "extent": {
    "spatial": {
      "bbox": [
        [
          -180.0,
          -90.0,
          180.0,
          90.0
        ]
      ]
    },
    "temporal": {
      "interval": [
        [
          "1981-01-01T00:00:00Z",
          null
        ]
      ]
    }
  },
  "license": "proprietary",
  "keywords": [
    "copernicus services",
    "sentinel hub",
    "xcube",
    "raster",
    "systematic",
    "machine learning",
    "land cover",
    "CLMS",
    "derived data",
    "open data"
  ],
  "providers": [
    {
      "name": "WEkEO",
      "description": "WEkEO DIAS",
      "roles": [
        "host"
      ],
      "url": "https://www.wekeo.eu/"
    }
  ]
}