<?xml version="1.0" encoding="UTF-8"?>
<gmd:MD_Metadata xmlns:gmd="http://www.isotc211.org/2005/gmd" xmlns:gco="http://www.isotc211.org/2005/gco" xmlns:srv="http://www.isotc211.org/2005/srv" xmlns:gmx="http://www.isotc211.org/2005/gmx" xmlns:gts="http://www.isotc211.org/2005/gts" xmlns:gsr="http://www.isotc211.org/2005/gsr" xmlns:gmi="http://www.isotc211.org/2005/gmi" xmlns:gml="http://www.opengis.net/gml/3.2" xmlns:xlink="http://www.w3.org/1999/xlink" xmlns:xsi="http://www.w3.org/2001/XMLSchema-instance" xsi:schemaLocation="http://www.isotc211.org/2005/gmd http://schemas.opengis.net/csw/2.0.2/profiles/apiso/1.0.0/apiso.xsd">
  <gmd:fileIdentifier>
    <gco:CharacterString>5884f314-84a9-4f53-a745-d94d7a53e8b1</gco:CharacterString>
  </gmd:fileIdentifier>
  <gmd:language xmlns:gml="http://www.opengis.net/gml">
    <gmd:LanguageCode codeList="http://www.loc.gov/standards/iso639-2/" codeListValue="eng" />
  </gmd:language>
  <gmd:characterSet xmlns:gml="http://www.opengis.net/gml">
    <gmd:MD_CharacterSetCode codeList="http://standards.iso.org/iso/19139/resources/gmxCodelists.xml#MD_CharacterSetCode" codeListValue="utf8" />
  </gmd:characterSet>
  <gmd:hierarchyLevel xmlns:gml="http://www.opengis.net/gml">
    <gmd:MD_ScopeCode codeList="http://standards.iso.org/iso/19139/resources/gmxCodelists.xml#MD_ScopeCode" codeListValue="series" />
  </gmd:hierarchyLevel>
  <gmd:contact>
    <gmd:CI_ResponsibleParty>
      <gmd:organisationName>
        <gco:CharacterString>European Environment Agency</gco:CharacterString>
      </gmd:organisationName>
      <gmd:contactInfo>
        <gmd:CI_Contact>
          <gmd:address>
            <gmd:CI_Address>
              <gmd:deliveryPoint>
                <gco:CharacterString>Kongens Nytorv 6</gco:CharacterString>
              </gmd:deliveryPoint>
              <gmd:city>
                <gco:CharacterString>Copenhagen</gco:CharacterString>
              </gmd:city>
              <gmd:administrativeArea>
                <gco:CharacterString>K</gco:CharacterString>
              </gmd:administrativeArea>
              <gmd:postalCode>
                <gco:CharacterString>1050</gco:CharacterString>
              </gmd:postalCode>
              <gmd:country>
                <gco:CharacterString>Denmark</gco:CharacterString>
              </gmd:country>
              <gmd:electronicMailAddress>
                <gco:CharacterString>sdi@eea.europa.eu</gco:CharacterString>
              </gmd:electronicMailAddress>
            </gmd:CI_Address>
          </gmd:address>
        </gmd:CI_Contact>
      </gmd:contactInfo>
      <gmd:role>
        <gmd:CI_RoleCode codeList="http://standards.iso.org/iso/19139/resources/gmxCodelists.xml#CI_RoleCode" codeListValue="pointOfContact" />
      </gmd:role>
    </gmd:CI_ResponsibleParty>
  </gmd:contact>
  <gmd:dateStamp xmlns:gml="http://www.opengis.net/gml">
    <gco:DateTime>2023-02-13T12:19:25.894Z</gco:DateTime>
  </gmd:dateStamp>
  <gmd:metadataStandardName xmlns:gml="http://www.opengis.net/gml">
    <gco:CharacterString>ISO 19115:2003/19139</gco:CharacterString>
  </gmd:metadataStandardName>
  <gmd:metadataStandardVersion xmlns:gml="http://www.opengis.net/gml">
    <gco:CharacterString>1.0</gco:CharacterString>
  </gmd:metadataStandardVersion>
  <gmd:identificationInfo xmlns:gml="http://www.opengis.net/gml">
    <gmd:MD_DataIdentification>
      <gmd:citation>
        <gmd:CI_Citation>
          <gmd:title>
            <gco:CharacterString>Vulnerability to climate change</gco:CharacterString>
          </gmd:title>
          <gmd:date xmlns:gml="http://www.opengis.net/gml/3.2">
            <gmd:CI_Date>
              <gmd:date>
                <gco:Date>2021-12-01</gco:Date>
              </gmd:date>
              <gmd:dateType>
                <gmd:CI_DateTypeCode codeList="http://standards.iso.org/iso/19139/resources/gmxCodelists.xml#CI_DateTypeCode" codeListValue="publication" />
              </gmd:dateType>
            </gmd:CI_Date>
          </gmd:date>
          <gmd:edition gco:nilReason="missing">
            <gco:CharacterString />
          </gmd:edition>
          <gmd:identifier>
            <gmd:MD_Identifier>
              <gmd:code>
                <gco:CharacterString>eea_vulnarability-climate-hazards_s</gco:CharacterString>
              </gmd:code>
            </gmd:MD_Identifier>
          </gmd:identifier>
          <gmd:identifier>
            <gmd:MD_Identifier>
              <gmd:code>
                <gco:CharacterString>DAT-19-en</gco:CharacterString>
              </gmd:code>
            </gmd:MD_Identifier>
          </gmd:identifier>
        </gmd:CI_Citation>
      </gmd:citation>
      <gmd:abstract>
        <gco:CharacterString>This series refers to datasets related to the propensity or predisposition to be adversely affected by climate change. These mainly include socio-economic and demographic variables.
Vulnerability encompasses a variety of concepts and elements including sensitivity or susceptibility to harm and lack of capacity to cope and adapt.
The dataset is part of the European Climate Adaptation Platform (Climate-ADAPT) accessible here: https://climate-adapt.eea.europa.eu/</gco:CharacterString>
      </gmd:abstract>
      <gmd:pointOfContact xmlns:gml="http://www.opengis.net/gml/3.2" gco:nilReason="withheld" />
      <gmd:pointOfContact xmlns:gml="http://www.opengis.net/gml/3.2">
        <gmd:CI_ResponsibleParty>
          <gmd:organisationName>
            <gco:CharacterString>European Environment Agency</gco:CharacterString>
          </gmd:organisationName>
          <gmd:positionName gco:nilReason="missing">
            <gco:CharacterString />
          </gmd:positionName>
          <gmd:contactInfo>
            <gmd:CI_Contact>
              <gmd:address>
                <gmd:CI_Address>
                  <gmd:deliveryPoint>
                    <gco:CharacterString>Kongens Nytorv 6</gco:CharacterString>
                  </gmd:deliveryPoint>
                  <gmd:city>
                    <gco:CharacterString>Copenhagen</gco:CharacterString>
                  </gmd:city>
                  <gmd:administrativeArea>
                    <gco:CharacterString>K</gco:CharacterString>
                  </gmd:administrativeArea>
                  <gmd:postalCode>
                    <gco:CharacterString>1050</gco:CharacterString>
                  </gmd:postalCode>
                  <gmd:country>
                    <gco:CharacterString>Denmark</gco:CharacterString>
                  </gmd:country>
                  <gmd:electronicMailAddress>
                    <gco:CharacterString>info@eea.europa.eu</gco:CharacterString>
                  </gmd:electronicMailAddress>
                </gmd:CI_Address>
              </gmd:address>
            </gmd:CI_Contact>
          </gmd:contactInfo>
          <gmd:role>
            <gmd:CI_RoleCode codeList="http://standards.iso.org/iso/19139/resources/gmxCodelists.xml#CI_RoleCode" codeListValue="custodian" />
          </gmd:role>
        </gmd:CI_ResponsibleParty>
      </gmd:pointOfContact>
      <gmd:pointOfContact xmlns:gml="http://www.opengis.net/gml/3.2" gco:nilReason="withheld" />
      <gmd:graphicOverview xmlns:gml="http://www.opengis.net/gml/3.2">
        <gmd:MD_BrowseGraphic>
          <gmd:fileName>
            <gco:CharacterString>https://sdi.eea.europa.eu/public/catalogue-graphic-overview/018a767a-9b66-401d-9d46-898648a928b6.png</gco:CharacterString>
          </gmd:fileName>
        </gmd:MD_BrowseGraphic>
      </gmd:graphicOverview>
      <gmd:graphicOverview xmlns:gml="http://www.opengis.net/gml/3.2">
        <gmd:MD_BrowseGraphic>
          <gmd:fileName>
            <gco:CharacterString>https://sdi.eea.europa.eu/public/catalogue-graphic-overview/2b345477-33df-491f-be4d-743bcdfc7274.png</gco:CharacterString>
          </gmd:fileName>
        </gmd:MD_BrowseGraphic>
      </gmd:graphicOverview>
      <gmd:graphicOverview xmlns:gml="http://www.opengis.net/gml/3.2">
        <gmd:MD_BrowseGraphic>
          <gmd:fileName>
            <gco:CharacterString>https://sdi.eea.europa.eu/public/catalogue-graphic-overview/38d868f5-f001-4dd8-99c0-920ce373f538.png</gco:CharacterString>
          </gmd:fileName>
        </gmd:MD_BrowseGraphic>
      </gmd:graphicOverview>
      <gmd:graphicOverview xmlns:gml="http://www.opengis.net/gml/3.2">
        <gmd:MD_BrowseGraphic>
          <gmd:fileName>
            <gco:CharacterString>https://sdi.eea.europa.eu/public/catalogue-graphic-overview/7cdb1475-eb2b-48f1-b7bb-6485bb4ed0f3.png</gco:CharacterString>
          </gmd:fileName>
        </gmd:MD_BrowseGraphic>
      </gmd:graphicOverview>
      <gmd:graphicOverview xmlns:gml="http://www.opengis.net/gml/3.2">
        <gmd:MD_BrowseGraphic>
          <gmd:fileName>
            <gco:CharacterString>https://sdi.eea.europa.eu/public/catalogue-graphic-overview/7e1af572-6668-4e2f-939a-74540ffc2e71.png</gco:CharacterString>
          </gmd:fileName>
          <gmd:fileDescription gco:nilReason="missing">
            <gco:CharacterString />
          </gmd:fileDescription>
          <gmd:fileType gco:nilReason="missing">
            <gco:CharacterString />
          </gmd:fileType>
        </gmd:MD_BrowseGraphic>
      </gmd:graphicOverview>
      <gmd:graphicOverview xmlns:gml="http://www.opengis.net/gml/3.2">
        <gmd:MD_BrowseGraphic>
          <gmd:fileName>
            <gco:CharacterString>https://sdi.eea.europa.eu/public/catalogue-graphic-overview/872ebd21-e550-427f-a5fd-d43097f016c5.png</gco:CharacterString>
          </gmd:fileName>
        </gmd:MD_BrowseGraphic>
      </gmd:graphicOverview>
      <gmd:graphicOverview xmlns:gml="http://www.opengis.net/gml/3.2">
        <gmd:MD_BrowseGraphic>
          <gmd:fileName>
            <gco:CharacterString>https://sdi.eea.europa.eu/public/catalogue-graphic-overview/b636bcdb-93bb-49f0-bec3-9e0275b561ee.png</gco:CharacterString>
          </gmd:fileName>
        </gmd:MD_BrowseGraphic>
      </gmd:graphicOverview>
      <gmd:graphicOverview xmlns:gml="http://www.opengis.net/gml/3.2">
        <gmd:MD_BrowseGraphic>
          <gmd:fileName>
            <gco:CharacterString>https://sdi.eea.europa.eu/public/catalogue-graphic-overview/be8ca950-d1ed-4690-a03d-3c6e8103bbe9.png</gco:CharacterString>
          </gmd:fileName>
        </gmd:MD_BrowseGraphic>
      </gmd:graphicOverview>
      <gmd:graphicOverview xmlns:gml="http://www.opengis.net/gml/3.2">
        <gmd:MD_BrowseGraphic>
          <gmd:fileName>
            <gco:CharacterString>https://sdi.eea.europa.eu/public/catalogue-graphic-overview/d82219d7-79bd-416b-81b7-c521c6cbc835.png</gco:CharacterString>
          </gmd:fileName>
        </gmd:MD_BrowseGraphic>
      </gmd:graphicOverview>
      <gmd:graphicOverview xmlns:gml="http://www.opengis.net/gml/3.2">
        <gmd:MD_BrowseGraphic>
          <gmd:fileName>
            <gco:CharacterString>https://sdi.eea.europa.eu/public/catalogue-graphic-overview/d84256cd-61f4-43dd-9a8d-5442aa54fbe3.png</gco:CharacterString>
          </gmd:fileName>
        </gmd:MD_BrowseGraphic>
      </gmd:graphicOverview>
      <gmd:descriptiveKeywords xmlns:gml="http://www.opengis.net/gml/3.2">
        <gmd:MD_Keywords>
          <gmd:keyword>
            <gco:CharacterString>Iceland</gco:CharacterString>
          </gmd:keyword>
          <gmd:keyword>
            <gco:CharacterString>Switzerland</gco:CharacterString>
          </gmd:keyword>
          <gmd:keyword>
            <gco:CharacterString>Liechtenstein</gco:CharacterString>
          </gmd:keyword>
          <gmd:keyword>
            <gco:CharacterString>United Kingdom</gco:CharacterString>
          </gmd:keyword>
          <gmd:keyword>
            <gco:CharacterString>EU27 (from 2020)</gco:CharacterString>
          </gmd:keyword>
          <gmd:keyword>
            <gco:CharacterString>Norway</gco:CharacterString>
          </gmd:keyword>
          <gmd:keyword>
            <gco:CharacterString>Türkiye</gco:CharacterString>
          </gmd:keyword>
          <gmd:type>
            <gmd:MD_KeywordTypeCode codeList="http://standards.iso.org/iso/19139/resources/gmxCodelists.xml#MD_KeywordTypeCode" codeListValue="place" />
          </gmd:type>
          <gmd:thesaurusName>
            <gmd:CI_Citation>
              <gmd:title>
                <gco:CharacterString>Continents, countries, sea regions of the world.</gco:CharacterString>
              </gmd:title>
              <gmd:date>
                <gmd:CI_Date>
                  <gmd:date>
                    <gco:Date>2015-07-17</gco:Date>
                  </gmd:date>
                  <gmd:dateType>
                    <gmd:CI_DateTypeCode codeList="http://standards.iso.org/iso/19139/resources/gmxCodelists.xml#CI_DateTypeCode" codeListValue="publication" />
                  </gmd:dateType>
                </gmd:CI_Date>
              </gmd:date>
              <gmd:identifier>
                <gmd:MD_Identifier>
                  <gmd:code>
                    <gmx:Anchor xlink:href="https://sdi.eea.europa.eu/catalogue/srv/api/registries/vocabularies/external.place.regions">geonetwork.thesaurus.external.place.regions</gmx:Anchor>
                  </gmd:code>
                </gmd:MD_Identifier>
              </gmd:identifier>
            </gmd:CI_Citation>
          </gmd:thesaurusName>
        </gmd:MD_Keywords>
      </gmd:descriptiveKeywords>
      <gmd:descriptiveKeywords xmlns:gml="http://www.opengis.net/gml/3.2">
        <gmd:MD_Keywords>
          <gmd:keyword>
            <gco:CharacterString>2009</gco:CharacterString>
          </gmd:keyword>
          <gmd:type>
            <gmd:MD_KeywordTypeCode codeList="http://standards.iso.org/iso/19139/resources/gmxCodelists.xml#MD_KeywordTypeCode" codeListValue="theme" />
          </gmd:type>
          <gmd:thesaurusName>
            <gmd:CI_Citation>
              <gmd:title>
                <gco:CharacterString>EEA Management Plan</gco:CharacterString>
              </gmd:title>
              <gmd:date>
                <gmd:CI_Date>
                  <gmd:date>
                    <gco:Date>2021-08-25</gco:Date>
                  </gmd:date>
                  <gmd:dateType>
                    <gmd:CI_DateTypeCode codeList="http://standards.iso.org/iso/19139/resources/gmxCodelists.xml#CI_DateTypeCode" codeListValue="publication" />
                  </gmd:dateType>
                </gmd:CI_Date>
              </gmd:date>
              <gmd:identifier>
                <gmd:MD_Identifier>
                  <gmd:code>
                    <gmx:Anchor xlink:href="https://sdi.eea.europa.eu/catalogue/srv/api/registries/vocabularies/local.theme.eea-mp">geonetwork.thesaurus.local.theme.eea-mp</gmx:Anchor>
                  </gmd:code>
                </gmd:MD_Identifier>
              </gmd:identifier>
            </gmd:CI_Citation>
          </gmd:thesaurusName>
        </gmd:MD_Keywords>
      </gmd:descriptiveKeywords>
      <gmd:descriptiveKeywords xmlns:gml="http://www.opengis.net/gml/3.2" gco:nilReason="withheld" />
      <gmd:descriptiveKeywords xmlns:gml="http://www.opengis.net/gml/3.2" gco:nilReason="withheld" />
      <gmd:descriptiveKeywords xmlns:gn="http://www.fao.org/geonetwork" xmlns:gml="http://www.opengis.net/gml/3.2">
        <gmd:MD_Keywords>
          <gmd:keyword>
            <gco:CharacterString>Climate adaptation</gco:CharacterString>
          </gmd:keyword>
          <gmd:keyword>
            <gco:CharacterString>Environmental health impacts</gco:CharacterString>
          </gmd:keyword>
          <gmd:type>
            <gmd:MD_KeywordTypeCode codeList="http://standards.iso.org/iso/19139/resources/gmxCodelists.xml#MD_KeywordTypeCode" codeListValue="theme" />
          </gmd:type>
          <gmd:thesaurusName>
            <gmd:CI_Citation>
              <gmd:title>
                <gco:CharacterString>EEA topics</gco:CharacterString>
              </gmd:title>
              <gmd:date>
                <gmd:CI_Date>
                  <gmd:date>
                    <gco:Date>2020-09-24</gco:Date>
                  </gmd:date>
                  <gmd:dateType>
                    <gmd:CI_DateTypeCode codeList="http://standards.iso.org/iso/19139/resources/gmxCodelists.xml#CI_DateTypeCode" codeListValue="publication" />
                  </gmd:dateType>
                </gmd:CI_Date>
              </gmd:date>
              <gmd:identifier>
                <gmd:MD_Identifier>
                  <gmd:code>
                    <gmx:Anchor xlink:href="https://sdi.eea.europa.eu/catalogue/srv/api/registries/vocabularies/external.theme.eea-topics">geonetwork.thesaurus.external.theme.eea-topics</gmx:Anchor>
                  </gmd:code>
                </gmd:MD_Identifier>
              </gmd:identifier>
            </gmd:CI_Citation>
          </gmd:thesaurusName>
        </gmd:MD_Keywords>
      </gmd:descriptiveKeywords>
      <gmd:descriptiveKeywords xmlns:gml="http://www.opengis.net/gml/3.2">
        <gmd:MD_Keywords>
          <gmd:keyword>
            <gco:CharacterString>human health</gco:CharacterString>
          </gmd:keyword>
          <gmd:keyword>
            <gco:CharacterString>urban population</gco:CharacterString>
          </gmd:keyword>
          <gmd:keyword>
            <gco:CharacterString>climate change impact</gco:CharacterString>
          </gmd:keyword>
          <gmd:keyword>
            <gco:CharacterString>demography</gco:CharacterString>
          </gmd:keyword>
          <gmd:keyword>
            <gco:CharacterString>environmental health hazard</gco:CharacterString>
          </gmd:keyword>
          <gmd:keyword>
            <gco:CharacterString>population distribution</gco:CharacterString>
          </gmd:keyword>
          <gmd:keyword>
            <gco:CharacterString>statistical data</gco:CharacterString>
          </gmd:keyword>
          <gmd:keyword>
            <gco:CharacterString>household</gco:CharacterString>
          </gmd:keyword>
          <gmd:keyword>
            <gco:CharacterString>age</gco:CharacterString>
          </gmd:keyword>
          <gmd:keyword>
            <gco:CharacterString>higher education</gco:CharacterString>
          </gmd:keyword>
          <gmd:keyword>
            <gco:CharacterString>unemployment</gco:CharacterString>
          </gmd:keyword>
          <gmd:keyword>
            <gco:CharacterString>population density</gco:CharacterString>
          </gmd:keyword>
          <gmd:keyword>
            <gco:CharacterString>climate change adaptation</gco:CharacterString>
          </gmd:keyword>
          <gmd:keyword>
            <gco:CharacterString>climate</gco:CharacterString>
          </gmd:keyword>
          <gmd:keyword>
            <gco:CharacterString>composition of population</gco:CharacterString>
          </gmd:keyword>
          <gmd:keyword>
            <gco:CharacterString>social aspects, population</gco:CharacterString>
          </gmd:keyword>
          <gmd:type>
            <gmd:MD_KeywordTypeCode codeList="http://standards.iso.org/iso/19139/resources/gmxCodelists.xml#MD_KeywordTypeCode" codeListValue="theme" />
          </gmd:type>
          <gmd:thesaurusName>
            <gmd:CI_Citation>
              <gmd:title>
                <gco:CharacterString>GEMET</gco:CharacterString>
              </gmd:title>
              <gmd:date>
                <gmd:CI_Date>
                  <gmd:date>
                    <gco:Date>2021-11-30</gco:Date>
                  </gmd:date>
                  <gmd:dateType>
                    <gmd:CI_DateTypeCode codeList="http://standards.iso.org/iso/19139/resources/gmxCodelists.xml#CI_DateTypeCode" codeListValue="publication" />
                  </gmd:dateType>
                </gmd:CI_Date>
              </gmd:date>
              <gmd:identifier>
                <gmd:MD_Identifier>
                  <gmd:code>
                    <gmx:Anchor xlink:href="https://sdi.eea.europa.eu/catalogue/srv/api/registries/vocabularies/external.theme.gemet">geonetwork.thesaurus.external.theme.gemet</gmx:Anchor>
                  </gmd:code>
                </gmd:MD_Identifier>
              </gmd:identifier>
            </gmd:CI_Citation>
          </gmd:thesaurusName>
        </gmd:MD_Keywords>
      </gmd:descriptiveKeywords>
      <gmd:descriptiveKeywords xmlns:gml="http://www.opengis.net/gml/3.2">
        <gmd:MD_Keywords>
          <gmd:keyword>
            <gmx:Anchor xlink:href="http://inspire.ec.europa.eu/theme/pd">Population distribution — demography</gmx:Anchor>
          </gmd:keyword>
          <gmd:keyword>
            <gmx:Anchor xlink:href="http://inspire.ec.europa.eu/theme/pd">Population distribution — demography</gmx:Anchor>
          </gmd:keyword>
          <gmd:keyword>
            <gmx:Anchor xlink:href="http://inspire.ec.europa.eu/theme/lc">Land cover</gmx:Anchor>
          </gmd:keyword>
          <gmd:keyword>
            <gmx:Anchor xlink:href="http://inspire.ec.europa.eu/theme/su">Statistical units</gmx:Anchor>
          </gmd:keyword>
          <gmd:type>
            <gmd:MD_KeywordTypeCode codeList="http://standards.iso.org/iso/19139/resources/gmxCodelists.xml#MD_KeywordTypeCode" codeListValue="theme" />
          </gmd:type>
          <gmd:thesaurusName>
            <gmd:CI_Citation>
              <gmd:title>
                <gmx:Anchor xlink:href="http://inspire.ec.europa.eu/theme">GEMET - INSPIRE themes, version 1.0</gmx:Anchor>
              </gmd:title>
              <gmd:date>
                <gmd:CI_Date>
                  <gmd:date>
                    <gco:Date>2008-06-01</gco:Date>
                  </gmd:date>
                  <gmd:dateType>
                    <gmd:CI_DateTypeCode codeList="http://standards.iso.org/iso/19139/resources/gmxCodelists.xml#CI_DateTypeCode" codeListValue="publication" />
                  </gmd:dateType>
                </gmd:CI_Date>
              </gmd:date>
              <gmd:identifier>
                <gmd:MD_Identifier>
                  <gmd:code>
                    <gmx:Anchor xlink:href="https://sdi.eea.europa.eu/catalogue/srv/api/registries/vocabularies/external.theme.httpinspireeceuropaeutheme-theme">geonetwork.thesaurus.external.theme.httpinspireeceuropaeutheme-theme</gmx:Anchor>
                  </gmd:code>
                </gmd:MD_Identifier>
              </gmd:identifier>
            </gmd:CI_Citation>
          </gmd:thesaurusName>
        </gmd:MD_Keywords>
      </gmd:descriptiveKeywords>
      <gmd:descriptiveKeywords xmlns:gml="http://www.opengis.net/gml/3.2">
        <gmd:MD_Keywords>
          <gmd:keyword>
            <gmx:Anchor xlink:href="http://inspire.ec.europa.eu/metadata-codelist/SpatialScope/european">European</gmx:Anchor>
          </gmd:keyword>
          <gmd:keyword>
            <gmx:Anchor xlink:href="http://inspire.ec.europa.eu/metadata-codelist/SpatialScope/european">European</gmx:Anchor>
          </gmd:keyword>
          <gmd:type>
            <gmd:MD_KeywordTypeCode codeList="http://standards.iso.org/iso/19139/resources/gmxCodelists.xml#MD_KeywordTypeCode" codeListValue="theme" />
          </gmd:type>
          <gmd:thesaurusName>
            <gmd:CI_Citation>
              <gmd:title>
                <gmx:Anchor xlink:href="http://inspire.ec.europa.eu/metadata-codelist/SpatialScope">Spatial scope</gmx:Anchor>
              </gmd:title>
              <gmd:date>
                <gmd:CI_Date>
                  <gmd:date>
                    <gco:Date>2019-05-22</gco:Date>
                  </gmd:date>
                  <gmd:dateType>
                    <gmd:CI_DateTypeCode codeList="http://standards.iso.org/iso/19139/resources/gmxCodelists.xml#CI_DateTypeCode" codeListValue="publication" />
                  </gmd:dateType>
                </gmd:CI_Date>
              </gmd:date>
              <gmd:identifier>
                <gmd:MD_Identifier>
                  <gmd:code>
                    <gmx:Anchor xlink:href="https://sdi.eea.europa.eu/catalogue/srv/api/registries/vocabularies/external.theme.httpinspireeceuropaeumetadatacodelistSpatialScope-SpatialScope">geonetwork.thesaurus.external.theme.httpinspireeceuropaeumetadatacodelistSpatialScope-SpatialScope</gmx:Anchor>
                  </gmd:code>
                </gmd:MD_Identifier>
              </gmd:identifier>
            </gmd:CI_Citation>
          </gmd:thesaurusName>
        </gmd:MD_Keywords>
      </gmd:descriptiveKeywords>
      <gmd:aggregationInfo>
        <gmd:MD_AggregateInformation>
          <gmd:aggregateDataSetIdentifier>
            <gmd:MD_Identifier>
              <gmd:code>
                <gco:CharacterString>7e1af572-6668-4e2f-939a-74540ffc2e71</gco:CharacterString>
              </gmd:code>
            </gmd:MD_Identifier>
          </gmd:aggregateDataSetIdentifier>
          <gmd:associationType>
            <gmd:DS_AssociationTypeCode codeList="http://standards.iso.org/iso/19139/resources/gmxCodelists.xml#DS_AssociationTypeCode" codeListValue="isComposedOf" />
          </gmd:associationType>
        </gmd:MD_AggregateInformation>
      </gmd:aggregationInfo>
      <gmd:aggregationInfo>
        <gmd:MD_AggregateInformation>
          <gmd:aggregateDataSetIdentifier>
            <gmd:MD_Identifier>
              <gmd:code>
                <gco:CharacterString>872ebd21-e550-427f-a5fd-d43097f016c5</gco:CharacterString>
              </gmd:code>
            </gmd:MD_Identifier>
          </gmd:aggregateDataSetIdentifier>
          <gmd:associationType>
            <gmd:DS_AssociationTypeCode codeList="http://standards.iso.org/iso/19139/resources/gmxCodelists.xml#DS_AssociationTypeCode" codeListValue="isComposedOf" />
          </gmd:associationType>
        </gmd:MD_AggregateInformation>
      </gmd:aggregationInfo>
      <gmd:aggregationInfo>
        <gmd:MD_AggregateInformation>
          <gmd:aggregateDataSetIdentifier>
            <gmd:MD_Identifier>
              <gmd:code>
                <gco:CharacterString>7cdb1475-eb2b-48f1-b7bb-6485bb4ed0f3</gco:CharacterString>
              </gmd:code>
            </gmd:MD_Identifier>
          </gmd:aggregateDataSetIdentifier>
          <gmd:associationType>
            <gmd:DS_AssociationTypeCode codeList="http://standards.iso.org/iso/19139/resources/gmxCodelists.xml#DS_AssociationTypeCode" codeListValue="isComposedOf" />
          </gmd:associationType>
        </gmd:MD_AggregateInformation>
      </gmd:aggregationInfo>
      <gmd:aggregationInfo>
        <gmd:MD_AggregateInformation>
          <gmd:aggregateDataSetIdentifier>
            <gmd:MD_Identifier>
              <gmd:code>
                <gco:CharacterString>b636bcdb-93bb-49f0-bec3-9e0275b561ee</gco:CharacterString>
              </gmd:code>
            </gmd:MD_Identifier>
          </gmd:aggregateDataSetIdentifier>
          <gmd:associationType>
            <gmd:DS_AssociationTypeCode codeList="http://standards.iso.org/iso/19139/resources/gmxCodelists.xml#DS_AssociationTypeCode" codeListValue="isComposedOf" />
          </gmd:associationType>
        </gmd:MD_AggregateInformation>
      </gmd:aggregationInfo>
      <gmd:aggregationInfo>
        <gmd:MD_AggregateInformation>
          <gmd:aggregateDataSetIdentifier>
            <gmd:MD_Identifier>
              <gmd:code>
                <gco:CharacterString>2b345477-33df-491f-be4d-743bcdfc7274</gco:CharacterString>
              </gmd:code>
            </gmd:MD_Identifier>
          </gmd:aggregateDataSetIdentifier>
          <gmd:associationType>
            <gmd:DS_AssociationTypeCode codeList="http://standards.iso.org/iso/19139/resources/gmxCodelists.xml#DS_AssociationTypeCode" codeListValue="isComposedOf" />
          </gmd:associationType>
        </gmd:MD_AggregateInformation>
      </gmd:aggregationInfo>
      <gmd:aggregationInfo>
        <gmd:MD_AggregateInformation>
          <gmd:aggregateDataSetIdentifier>
            <gmd:MD_Identifier>
              <gmd:code>
                <gco:CharacterString>ca6b278c-528d-4a80-a274-500cdf5e7bf5</gco:CharacterString>
              </gmd:code>
            </gmd:MD_Identifier>
          </gmd:aggregateDataSetIdentifier>
          <gmd:associationType>
            <gmd:DS_AssociationTypeCode codeList="http://standards.iso.org/iso/19139/resources/gmxCodelists.xml#DS_AssociationTypeCode" codeListValue="isComposedOf" />
          </gmd:associationType>
        </gmd:MD_AggregateInformation>
      </gmd:aggregationInfo>
      <gmd:aggregationInfo>
        <gmd:MD_AggregateInformation>
          <gmd:aggregateDataSetIdentifier>
            <gmd:MD_Identifier>
              <gmd:code>
                <gco:CharacterString>018a767a-9b66-401d-9d46-898648a928b6</gco:CharacterString>
              </gmd:code>
            </gmd:MD_Identifier>
          </gmd:aggregateDataSetIdentifier>
          <gmd:associationType>
            <gmd:DS_AssociationTypeCode codeList="http://standards.iso.org/iso/19139/resources/gmxCodelists.xml#DS_AssociationTypeCode" codeListValue="isComposedOf" />
          </gmd:associationType>
        </gmd:MD_AggregateInformation>
      </gmd:aggregationInfo>
      <gmd:aggregationInfo>
        <gmd:MD_AggregateInformation>
          <gmd:aggregateDataSetIdentifier>
            <gmd:MD_Identifier>
              <gmd:code>
                <gco:CharacterString>be8ca950-d1ed-4690-a03d-3c6e8103bbe9</gco:CharacterString>
              </gmd:code>
            </gmd:MD_Identifier>
          </gmd:aggregateDataSetIdentifier>
          <gmd:associationType>
            <gmd:DS_AssociationTypeCode codeList="http://standards.iso.org/iso/19139/resources/gmxCodelists.xml#DS_AssociationTypeCode" codeListValue="isComposedOf" />
          </gmd:associationType>
        </gmd:MD_AggregateInformation>
      </gmd:aggregationInfo>
      <gmd:aggregationInfo>
        <gmd:MD_AggregateInformation>
          <gmd:aggregateDataSetIdentifier>
            <gmd:MD_Identifier>
              <gmd:code>
                <gco:CharacterString>d84256cd-61f4-43dd-9a8d-5442aa54fbe3</gco:CharacterString>
              </gmd:code>
            </gmd:MD_Identifier>
          </gmd:aggregateDataSetIdentifier>
          <gmd:associationType>
            <gmd:DS_AssociationTypeCode codeList="http://standards.iso.org/iso/19139/resources/gmxCodelists.xml#DS_AssociationTypeCode" codeListValue="isComposedOf" />
          </gmd:associationType>
        </gmd:MD_AggregateInformation>
      </gmd:aggregationInfo>
      <gmd:aggregationInfo>
        <gmd:MD_AggregateInformation>
          <gmd:aggregateDataSetIdentifier>
            <gmd:MD_Identifier>
              <gmd:code>
                <gco:CharacterString>d82219d7-79bd-416b-81b7-c521c6cbc835</gco:CharacterString>
              </gmd:code>
            </gmd:MD_Identifier>
          </gmd:aggregateDataSetIdentifier>
          <gmd:associationType>
            <gmd:DS_AssociationTypeCode codeList="http://standards.iso.org/iso/19139/resources/gmxCodelists.xml#DS_AssociationTypeCode" codeListValue="isComposedOf" />
          </gmd:associationType>
        </gmd:MD_AggregateInformation>
      </gmd:aggregationInfo>
      <gmd:spatialRepresentationType xmlns:gml="http://www.opengis.net/gml/3.2">
        <gmd:MD_SpatialRepresentationTypeCode codeList="http://standards.iso.org/iso/19139/resources/gmxCodelists.xml#MD_SpatialRepresentationTypeCode" codeListValue="grid" />
      </gmd:spatialRepresentationType>
      <gmd:spatialRepresentationType xmlns:gml="http://www.opengis.net/gml/3.2">
        <gmd:MD_SpatialRepresentationTypeCode codeList="http://standards.iso.org/iso/19139/resources/gmxCodelists.xml#MD_SpatialRepresentationTypeCode" codeListValue="vector" />
      </gmd:spatialRepresentationType>
      <gmd:spatialResolution xmlns:gml="http://www.opengis.net/gml/3.2">
        <gmd:MD_Resolution>
          <gmd:equivalentScale>
            <gmd:MD_RepresentativeFraction>
              <gmd:denominator>
                <gco:Integer>100000</gco:Integer>
              </gmd:denominator>
            </gmd:MD_RepresentativeFraction>
          </gmd:equivalentScale>
        </gmd:MD_Resolution>
      </gmd:spatialResolution>
      <gmd:spatialResolution xmlns:gn="http://www.fao.org/geonetwork" xmlns:gml="http://www.opengis.net/gml/3.2">
        <gmd:MD_Resolution>
          <gmd:equivalentScale>
            <gmd:MD_RepresentativeFraction>
              <gmd:denominator>
                <gco:Integer>1000000</gco:Integer>
              </gmd:denominator>
            </gmd:MD_RepresentativeFraction>
          </gmd:equivalentScale>
        </gmd:MD_Resolution>
      </gmd:spatialResolution>
      <gmd:language xmlns:gml="http://www.opengis.net/gml/3.2">
        <gmd:LanguageCode codeList="http://www.loc.gov/standards/iso639-2/" codeListValue="eng" />
      </gmd:language>
      <gmd:characterSet xmlns:gml="http://www.opengis.net/gml/3.2">
        <gmd:MD_CharacterSetCode codeList="http://standards.iso.org/iso/19139/resources/gmxCodelists.xml#MD_CharacterSetCode" codeListValue="utf8" />
      </gmd:characterSet>
      <gmd:topicCategory>
        <gmd:MD_TopicCategoryCode>environment</gmd:MD_TopicCategoryCode>
      </gmd:topicCategory>
      <gmd:topicCategory>
        <gmd:MD_TopicCategoryCode>geoscientificInformation</gmd:MD_TopicCategoryCode>
      </gmd:topicCategory>
      <gmd:topicCategory>
        <gmd:MD_TopicCategoryCode>society</gmd:MD_TopicCategoryCode>
      </gmd:topicCategory>
      <gmd:extent>
        <gmd:EX_Extent>
          <gmd:geographicElement xmlns:gml="http://www.opengis.net/gml/3.2">
            <gmd:EX_GeographicBoundingBox>
              <gmd:westBoundLongitude>
                <gco:Decimal>-21.67</gco:Decimal>
              </gmd:westBoundLongitude>
              <gmd:eastBoundLongitude>
                <gco:Decimal>33.38</gco:Decimal>
              </gmd:eastBoundLongitude>
              <gmd:southBoundLatitude>
                <gco:Decimal>28.98</gco:Decimal>
              </gmd:southBoundLatitude>
              <gmd:northBoundLatitude>
                <gco:Decimal>69.64</gco:Decimal>
              </gmd:northBoundLatitude>
            </gmd:EX_GeographicBoundingBox>
          </gmd:geographicElement>
          <gmd:geographicElement xmlns:gml="http://www.opengis.net/gml/3.2">
            <gmd:EX_GeographicBoundingBox>
              <gmd:westBoundLongitude>
                <gco:Decimal>-21.68</gco:Decimal>
              </gmd:westBoundLongitude>
              <gmd:eastBoundLongitude>
                <gco:Decimal>33.38</gco:Decimal>
              </gmd:eastBoundLongitude>
              <gmd:southBoundLatitude>
                <gco:Decimal>28.97</gco:Decimal>
              </gmd:southBoundLatitude>
              <gmd:northBoundLatitude>
                <gco:Decimal>69.64</gco:Decimal>
              </gmd:northBoundLatitude>
            </gmd:EX_GeographicBoundingBox>
          </gmd:geographicElement>
          <gmd:geographicElement xmlns:gml="http://www.opengis.net/gml/3.2">
            <gmd:EX_GeographicBoundingBox>
              <gmd:westBoundLongitude>
                <gco:Decimal>-33.1144</gco:Decimal>
              </gmd:westBoundLongitude>
              <gmd:eastBoundLongitude>
                <gco:Decimal>32.7966</gco:Decimal>
              </gmd:eastBoundLongitude>
              <gmd:southBoundLatitude>
                <gco:Decimal>26.2762</gco:Decimal>
              </gmd:southBoundLatitude>
              <gmd:northBoundLatitude>
                <gco:Decimal>73.6275</gco:Decimal>
              </gmd:northBoundLatitude>
            </gmd:EX_GeographicBoundingBox>
          </gmd:geographicElement>
          <gmd:geographicElement xmlns:gml="http://www.opengis.net/gml/3.2">
            <gmd:EX_GeographicBoundingBox>
              <gmd:westBoundLongitude>
                <gco:Decimal>-33.90432</gco:Decimal>
              </gmd:westBoundLongitude>
              <gmd:eastBoundLongitude>
                <gco:Decimal>38.1471</gco:Decimal>
              </gmd:eastBoundLongitude>
              <gmd:southBoundLatitude>
                <gco:Decimal>26.988714</gco:Decimal>
              </gmd:southBoundLatitude>
              <gmd:northBoundLatitude>
                <gco:Decimal>60.57849</gco:Decimal>
              </gmd:northBoundLatitude>
            </gmd:EX_GeographicBoundingBox>
          </gmd:geographicElement>
          <gmd:geographicElement xmlns:gml="http://www.opengis.net/gml/3.2">
            <gmd:EX_GeographicBoundingBox>
              <gmd:westBoundLongitude>
                <gco:Decimal>-54.9204</gco:Decimal>
              </gmd:westBoundLongitude>
              <gmd:eastBoundLongitude>
                <gco:Decimal>70.765</gco:Decimal>
              </gmd:eastBoundLongitude>
              <gmd:southBoundLatitude>
                <gco:Decimal>24.8029</gco:Decimal>
              </gmd:southBoundLatitude>
              <gmd:northBoundLatitude>
                <gco:Decimal>71.8969</gco:Decimal>
              </gmd:northBoundLatitude>
            </gmd:EX_GeographicBoundingBox>
          </gmd:geographicElement>
          <gmd:geographicElement xmlns:gml="http://www.opengis.net/gml/3.2">
            <gmd:EX_GeographicBoundingBox>
              <gmd:westBoundLongitude>
                <gco:Decimal>-60.98</gco:Decimal>
              </gmd:westBoundLongitude>
              <gmd:eastBoundLongitude>
                <gco:Decimal>33.38</gco:Decimal>
              </gmd:eastBoundLongitude>
              <gmd:southBoundLatitude>
                <gco:Decimal>28.97</gco:Decimal>
              </gmd:southBoundLatitude>
              <gmd:northBoundLatitude>
                <gco:Decimal>69.73</gco:Decimal>
              </gmd:northBoundLatitude>
            </gmd:EX_GeographicBoundingBox>
          </gmd:geographicElement>
          <gmd:geographicElement xmlns:gml="http://www.opengis.net/gml/3.2">
            <gmd:EX_GeographicBoundingBox>
              <gmd:westBoundLongitude>
                <gco:Decimal>-61.04</gco:Decimal>
              </gmd:westBoundLongitude>
              <gmd:eastBoundLongitude>
                <gco:Decimal>55.50</gco:Decimal>
              </gmd:eastBoundLongitude>
              <gmd:southBoundLatitude>
                <gco:Decimal>-20.94</gco:Decimal>
              </gmd:southBoundLatitude>
              <gmd:northBoundLatitude>
                <gco:Decimal>69.64</gco:Decimal>
              </gmd:northBoundLatitude>
            </gmd:EX_GeographicBoundingBox>
          </gmd:geographicElement>
          <gmd:geographicElement xmlns:gml="http://www.opengis.net/gml/3.2">
            <gmd:EX_GeographicBoundingBox>
              <gmd:westBoundLongitude>
                <gco:Decimal>-81.7831</gco:Decimal>
              </gmd:westBoundLongitude>
              <gmd:eastBoundLongitude>
                <gco:Decimal>93.1754</gco:Decimal>
              </gmd:eastBoundLongitude>
              <gmd:southBoundLatitude>
                <gco:Decimal>-29.8581</gco:Decimal>
              </gmd:southBoundLatitude>
              <gmd:northBoundLatitude>
                <gco:Decimal>71.8969</gco:Decimal>
              </gmd:northBoundLatitude>
            </gmd:EX_GeographicBoundingBox>
          </gmd:geographicElement>
          <gmd:temporalElement xmlns:gml="http://www.opengis.net/gml/3.2">
            <gmd:EX_TemporalExtent>
              <gmd:extent>
                <gml:TimePeriod gml:id="d28e322a1049886">
                  <gml:beginPosition>2000-01-01</gml:beginPosition>
                  <gml:endPosition>2000-12-31</gml:endPosition>
                </gml:TimePeriod>
              </gmd:extent>
            </gmd:EX_TemporalExtent>
          </gmd:temporalElement>
          <gmd:temporalElement xmlns:gml="http://www.opengis.net/gml/3.2">
            <gmd:EX_TemporalExtent>
              <gmd:extent>
                <gml:TimePeriod gml:id="d28e322a1049886">
                  <gml:beginPosition>2005-12-31</gml:beginPosition>
                  <gml:endPosition>2007-01-01</gml:endPosition>
                </gml:TimePeriod>
              </gmd:extent>
            </gmd:EX_TemporalExtent>
          </gmd:temporalElement>
          <gmd:temporalElement xmlns:gml="http://www.opengis.net/gml/3.2">
            <gmd:EX_TemporalExtent>
              <gmd:extent>
                <gml:TimePeriod gml:id="d17964e856a1052958">
                  <gml:beginPosition>2014-01-01</gml:beginPosition>
                  <gml:endPosition>2014-12-31</gml:endPosition>
                </gml:TimePeriod>
              </gmd:extent>
            </gmd:EX_TemporalExtent>
          </gmd:temporalElement>
          <gmd:temporalElement xmlns:gml="http://www.opengis.net/gml/3.2">
            <gmd:EX_TemporalExtent>
              <gmd:extent>
                <gml:TimePeriod gml:id="d17964e856a1052958">
                  <gml:beginPosition>2019-01-01</gml:beginPosition>
                  <gml:endPosition>2020-12-31</gml:endPosition>
                </gml:TimePeriod>
              </gmd:extent>
            </gmd:EX_TemporalExtent>
          </gmd:temporalElement>
        </gmd:EX_Extent>
      </gmd:extent>
    </gmd:MD_DataIdentification>
  </gmd:identificationInfo>
</gmd:MD_Metadata>

