{
    "type": "Collection",
    "stac_version": "0.9.0",
    "stac_extensions": [
        "datacube"
    ],
    "id": "S2_L2A_BURUNDI",
    "title": "S2_L2A_BURUNDI",
    "description": "Sentinel-2 Data",
    "extent": {
        "spatial": {
            "bbox": [
                [
                    28.797583105342234,
                    -2.801528275532386,
                    29.785937865667453,
                    -1.8071273649454704
                ]
            ]
        },
        "temporal": {
            "interval": [
                [
                    "2017-01-18T08:18:45.847Z",
                    "2020-12-28T08:30:51.816545Z"
                ]
            ]
        }
    },
    "providers": [
        {
            "name": "Eurac EO ODC",
            "url": "http://www.eurac.edu/",
            "roles": [
                "producer",
                "host"
            ]
        }
    ],
    "license": "CC-BY-4.0",
    "links": [
        {
            "rel": "license",
            "href": "https://creativecommons.org/licenses/by/4.0/",
            "type": "text/html",
            "title": "License link"
        }
    ],
    "cube:dimensions": {
        "DATE": {
            "type": "temporal",
            "extent": [
                "2017-01-18T08:18:45.847000+00:00",
                "2020-12-28T08:30:51.816545+00:00"
            ]
        },
        "X": {
            "type": "spatial",
            "axis": "x",
            "extent": [
                28.797583105342234,
                29.785937865667453
            ],
            "reference_system": 32735
        },
        "Y": {
            "type": "spatial",
            "axis": "y",
            "extent": [
                -2.801528275532386,
                -1.8071273649454704
            ],
            "reference_system": 32735
        },
        "bands": {
            "type": "bands",
            "values": [
                "FMASK",
                "AOT_10m",
                "AOT_20m",
                "AOT_60m",
                "B01_60m",
                "B02_10m",
                "B02_20m",
                "B02_60m",
                "B03_10m",
                "B03_20m",
                "B03_60m",
                "B04_10m",
                "B04_20m",
                "B04_60m",
                "B05_20m",
                "B05_60m",
                "B06_20m",
                "B06_60m",
                "B07_20m",
                "B07_60m",
                "B08_10m",
                "B09_60m",
                "B11_20m",
                "B11_60m",
                "B12_20m",
                "B12_60m",
                "B8A_20m",
                "B8A_60m",
                "SCL_20m",
                "SCL_60m",
                "WVP_10m",
                "WVP_20m",
                "WVP_60m"
            ]
        }
    }
}