{
  "type": "Collection",
  "id": "CGIAR/SRTM90_V4",
  "stac_version": "1.0.0",
  "description": "The Shuttle Radar Topography Mission (SRTM) digital\nelevation dataset was originally produced to provide consistent,\nhigh-quality elevation data at near global scope. This version\nof the SRTM digital elevation data has been processed to fill data\nvoids, and to facilitate its ease of use.\n",
  "links": [],
  "title": "SRTM Digital Elevation Data Version 4",
  "extent": {
    "spatial": {
      "bbox": [
        [
          -180.0,
          -90.0,
          180.0,
          90.0
        ]
      ]
    },
    "temporal": {
      "interval": [
        [
          "1981-01-01T00:00:00Z",
          null
        ]
      ]
    }
  },
  "license": "proprietary",
  "keywords": [
    "cgiar",
    "dem",
    "elevation",
    "geophysical",
    "srtm",
    "topography"
  ],
  "providers": [
    {
      "name": "WEkEO",
      "description": "WEkEO DIAS",
      "roles": [
        "host"
      ],
      "url": "https://www.wekeo.eu/"
    }
  ]
}