<gmi:MI_Metadata xmlns="http://www.isotc211.org/2005/gmd" xmlns:date="http://exslt.org/dates-and-times" xmlns:eum="http://www.eumetsat.int/2008/gmi" xmlns:fn="http://www.w3.org/TR/xpath-functions" xmlns:gco="http://www.isotc211.org/2005/gco" xmlns:gmd="http://www.isotc211.org/2005/gmd" xmlns:gmi="http://www.isotc211.org/2005/gmi" xmlns:gml="http://www.opengis.net/gml" xmlns:gmx="http://www.isotc211.org/2005/gmx" xmlns:str="http://exslt.org/strings" xmlns:xdt="http://www.w3.org/2005/02/xpath-datatypes" xmlns:xlink="http://www.w3.org/1999/xlink" xmlns:xs="http://www.w3.org/2001/XMLSchema" xmlns:xsi="http://www.w3.org/2001/XMLSchema-instance" xmlns:csw="http://www.opengis.net/cat/csw/2.0.2" xsi:schemaLocation="http://www.eumetsat.int/2008/gmi http://navigator.eumetsat.int/discovery/rest/schemas/eum/eum.xsd">
      <gmd:fileIdentifier>
        <gco:CharacterString>EO:EUM:DAT:0593</gco:CharacterString>
      </gmd:fileIdentifier>
      <gmd:language>
        <LanguageCode codeList="http://www.w3.org/WAI/ER/IG/ert/iso639.htm" codeListValue="eng"/>
      </gmd:language>
      <gmd:hierarchyLevel>
        <MD_ScopeCode codeList="http://standards.iso.org/ittf/PubliclyAvailableStandards/ISO_19139_Schemas/resources/codelist/gmxCodelists.xml#MD_ScopeCode" codeListValue="series"/>
      </gmd:hierarchyLevel>
      <gmd:hierarchyLevelName>
        <gco:CharacterString>theme.par.Ocean</gco:CharacterString>
      </gmd:hierarchyLevelName>
      <gmd:hierarchyLevelName>
        <gco:CharacterString>theme.par.Ocean_Colour</gco:CharacterString>
      </gmd:hierarchyLevelName>
      <gmd:hierarchyLevelName>
        <gco:CharacterString>theme.par.Radiation</gco:CharacterString>
      </gmd:hierarchyLevelName>
      <gmd:hierarchyLevelName>
        <gco:CharacterString>theme.par.Level_2_Data</gco:CharacterString>
      </gmd:hierarchyLevelName>
      <gmd:hierarchyLevelName>
        <gco:CharacterString>dis.Download</gco:CharacterString>
      </gmd:hierarchyLevelName>
      <gmd:hierarchyLevelName>
        <gco:CharacterString>sat.Sentinel-3</gco:CharacterString>
      </gmd:hierarchyLevelName>
      <gmd:contact>
        <gmd:CI_ResponsibleParty>
          <gmd:individualName>
            <gco:CharacterString>European Organisation for the Exploitation of Meteorological Satellites</gco:CharacterString>
          </gmd:individualName>
          <gmd:organisationName>
            <gco:CharacterString>EUMETSAT for Copernicus</gco:CharacterString>
          </gmd:organisationName>
          <gmd:contactInfo>
            <gmd:CI_Contact>
              <gmd:phone>
                <gmd:CI_Telephone>
                  <gmd:voice>
                    <gco:CharacterString>+49(0)6151-807 3660/3770</gco:CharacterString>
                  </gmd:voice>
                  <gmd:facsimile>
                    <gco:CharacterString>+49(0)6151-807 3790</gco:CharacterString>
                  </gmd:facsimile>
                </gmd:CI_Telephone>
              </gmd:phone>
              <gmd:address>
                <gmd:CI_Address>
                  <gmd:deliveryPoint>
                    <gco:CharacterString>EUMETSAT Allee 1</gco:CharacterString>
                  </gmd:deliveryPoint>
                  <gmd:city>
                    <gco:CharacterString>Darmstadt</gco:CharacterString>
                  </gmd:city>
                  <gmd:administrativeArea>
                    <gco:CharacterString>Hessen</gco:CharacterString>
                  </gmd:administrativeArea>
                  <gmd:postalCode>
                    <gco:CharacterString>64295</gco:CharacterString>
                  </gmd:postalCode>
                  <gmd:country>
                    <gco:CharacterString>Germany</gco:CharacterString>
                  </gmd:country>
                  <gmd:electronicMailAddress>
                    <gco:CharacterString>ops@eumetsat.int</gco:CharacterString>
                  </gmd:electronicMailAddress>
                </gmd:CI_Address>
              </gmd:address>
              <gmd:onlineResource>
                <gmd:CI_OnlineResource>
                  <gmd:linkage>
                    <gmd:URL>http://www.eumetsat.int</gmd:URL>
                  </gmd:linkage>
                </gmd:CI_OnlineResource>
              </gmd:onlineResource>
            </gmd:CI_Contact>
          </gmd:contactInfo>
          <gmd:role>
            <gmd:CI_RoleCode codeList="http://standards.iso.org/ittf/PubliclyAvailableStandards/ISO_19139_Schemas/resources/Codelist/ML_gmxCodelists.xml#MD_ScopeCode" codeListValue="pointOfContact">pointOfContact</gmd:CI_RoleCode>
          </gmd:role>
        </gmd:CI_ResponsibleParty>
      </gmd:contact>
      <gmd:dateStamp>
        <gco:Date>2023-05-08</gco:Date>
      </gmd:dateStamp>
      <gmd:metadataStandardName>
        <gco:CharacterString>ISO19115</gco:CharacterString>
      </gmd:metadataStandardName>
      <gmd:metadataStandardVersion>
        <gco:CharacterString>2003/Cor.1:2006</gco:CharacterString>
      </gmd:metadataStandardVersion>
      <gmd:identificationInfo>
        <gmd:MD_DataIdentification>
          <gmd:citation>
            <gmd:CI_Citation>
              <gmd:title>
                <gco:CharacterString>OLCI Level 2 Ocean Colour Reduced Resolution (version BC002) - Sentinel-3 - Reprocessed</gco:CharacterString>
              </gmd:title>
              <gmd:alternateTitle>
                <gco:CharacterString>OL_2_WRRBC002</gco:CharacterString>
              </gmd:alternateTitle>
              <gmd:alternateTitle>
                <gco:CharacterString>OL_2_WRR___</gco:CharacterString>
              </gmd:alternateTitle>
              <gmd:date>
                <gmd:CI_Date>
                  <gmd:date>
                    <gco:Date>2022-09-27</gco:Date>
                  </gmd:date>
                  <gmd:dateType>
                    <gmd:CI_DateTypeCode codeList="http://standards.iso.org/ittf/PubliclyAvailableStandards/ISO_19139_Schemas/resources/Codelist/gmxCodelists.xml#CI_DateTypeCode" codeListValue="creation"/>
                  </gmd:dateType>
                </gmd:CI_Date>
              </gmd:date>
              <edition>
                <gco:CharacterString>BC002</gco:CharacterString>
              </edition>
              <gmd:identifier>
                <gmd:MD_Identifier>
                  <gmd:code>
                    <gco:CharacterString>EO:EUM:DAT:0593</gco:CharacterString>
                  </gmd:code>
                </gmd:MD_Identifier>
              </gmd:identifier>
              <gmd:identifier>
                <gmd:RS_Identifier>
                  <gmd:code>
                    <gco:CharacterString>10.15770/EUM_SEC_CLM_0070</gco:CharacterString>
                  </gmd:code>
                  <gmd:codeSpace>
                    <gco:CharacterString>http://datacite.org</gco:CharacterString>
                  </gmd:codeSpace>
                </gmd:RS_Identifier>
              </gmd:identifier>
              <gmd:citedResponsibleParty>
                <gmd:CI_ResponsibleParty>
                  <individualName>
                    <gco:CharacterString>EUMETSAT for Copernicus</gco:CharacterString>
                  </individualName>
                  <gmd:role>
                    <gmd:CI_RoleCode codeList="http://navigator.eumetsat.int/metadata_schema/eum/resources/Codelist/eum_gmxCodelists.xml#CI_RoleCode" codeListValue="authorDetails"/>
                  </gmd:role>
                </gmd:CI_ResponsibleParty>
              </gmd:citedResponsibleParty>
              <gmd:citedResponsibleParty>
                <gmd:CI_ResponsibleParty>
                  <gmd:contactInfo>
                    <gmd:CI_Contact>
                      <gmd:onlineResource>
                        <gmd:CI_OnlineResource>
                          <gmd:linkage>
                            <gmd:URL>https://www.eumetsat.int/ocean-colour-services</gmd:URL>
                          </gmd:linkage>
                          <gmd:name>
                            <gco:CharacterString>Ocean colour services</gco:CharacterString>
                          </gmd:name>
                          <gmd:function>
                            <gmd:CI_OnLineFunctionCode codeList="http://standards.iso.org/ittf/PubliclyAvailableStandards/ISO_19139_Schemas/resources/Codelist/gmxCodelists.xml#CI_OnLineFunctionCode" codeListValue="information"/>
                          </gmd:function>
                        </gmd:CI_OnlineResource>
                      </gmd:onlineResource>
                    </gmd:CI_Contact>
                  </gmd:contactInfo>
                  <gmd:role>
                    <gmd:CI_RoleCode codeList="http://standards.iso.org/ittf/PubliclyAvailableStandards/ISO_19139_Schemas/resources/Codelist/gmxCodelists.xml#CI_RoleCode" codeListValue="author"/>
                  </gmd:role>
                </gmd:CI_ResponsibleParty>
              </gmd:citedResponsibleParty>
              <gmd:citedResponsibleParty>
                <gmd:CI_ResponsibleParty>
                  <gmd:contactInfo>
                    <gmd:CI_Contact>
                      <gmd:onlineResource>
                        <gmd:CI_OnlineResource>
                          <gmd:linkage>
                            <gmd:URL>https://metis.eumetsat.int/oc/</gmd:URL>
                          </gmd:linkage>
                          <gmd:name>
                            <gco:CharacterString>METIS Ocean Colour</gco:CharacterString>
                          </gmd:name>
                          <gmd:function>
                            <gmd:CI_OnLineFunctionCode codeList="http://standards.iso.org/ittf/PubliclyAvailableStandards/ISO_19139_Schemas/resources/Codelist/gmxCodelists.xml#CI_OnLineFunctionCode" codeListValue="information"/>
                          </gmd:function>
                        </gmd:CI_OnlineResource>
                      </gmd:onlineResource>
                    </gmd:CI_Contact>
                  </gmd:contactInfo>
                  <gmd:role>
                    <gmd:CI_RoleCode codeList="http://standards.iso.org/ittf/PubliclyAvailableStandards/ISO_19139_Schemas/resources/Codelist/gmxCodelists.xml#CI_RoleCode" codeListValue="author"/>
                  </gmd:role>
                </gmd:CI_ResponsibleParty>
              </gmd:citedResponsibleParty>
              <gmd:citedResponsibleParty>
                <gmd:CI_ResponsibleParty>
                  <gmd:contactInfo>
                    <gmd:CI_Contact>
                      <gmd:onlineResource>
                        <gmd:CI_OnlineResource>
                          <gmd:linkage>
                            <gmd:URL>http://doi.org/10.15770/EUM_SEC_CLM_0070</gmd:URL>
                          </gmd:linkage>
                          <gmd:name>
                            <gco:CharacterString>Digital Object Identifier (DOI): 10.15770/EUM_SEC_CLM_0070</gco:CharacterString>
                          </gmd:name>
                          <gmd:function>
                            <gmd:CI_OnLineFunctionCode codeList="http://standards.iso.org/ittf/PubliclyAvailableStandards/ISO_19139_Schemas/resources/Codelist/gmxCodelists.xml#CI_OnLineFunctionCode" codeListValue="information"/>
                          </gmd:function>
                        </gmd:CI_OnlineResource>
                      </gmd:onlineResource>
                    </gmd:CI_Contact>
                  </gmd:contactInfo>
                  <gmd:role>
                    <gmd:CI_RoleCode codeList="http://standards.iso.org/ittf/PubliclyAvailableStandards/ISO_19139_Schemas/resources/Codelist/gmxCodelists.xml#CI_RoleCode" codeListValue="author"/>
                  </gmd:role>
                </gmd:CI_ResponsibleParty>
              </gmd:citedResponsibleParty>
              <gmd:citedResponsibleParty>
                <gmd:CI_ResponsibleParty>
                  <gmd:contactInfo>
                    <gmd:CI_Contact>
                      <gmd:onlineResource>
                        <gmd:CI_OnlineResource>
                          <gmd:linkage>
                            <gmd:URL>https://eumetsatspace.atlassian.net/wiki/spaces/SEN3/overview</gmd:URL>
                          </gmd:linkage>
                          <gmd:name>
                            <gco:CharacterString>Sentinel-3 Knowledge Base</gco:CharacterString>
                          </gmd:name>
                          <gmd:function>
                            <gmd:CI_OnLineFunctionCode codeList="http://standards.iso.org/ittf/PubliclyAvailableStandards/ISO_19139_Schemas/resources/Codelist/gmxCodelists.xml#CI_OnLineFunctionCode" codeListValue="information"/>
                          </gmd:function>
                        </gmd:CI_OnlineResource>
                      </gmd:onlineResource>
                    </gmd:CI_Contact>
                  </gmd:contactInfo>
                  <gmd:role>
                    <gmd:CI_RoleCode codeList="http://standards.iso.org/ittf/PubliclyAvailableStandards/ISO_19139_Schemas/resources/Codelist/gmxCodelists.xml#CI_RoleCode" codeListValue="author"/>
                  </gmd:role>
                </gmd:CI_ResponsibleParty>
              </gmd:citedResponsibleParty>
              <gmd:citedResponsibleParty>
                <gmd:CI_ResponsibleParty>
                  <gmd:contactInfo>
                    <gmd:CI_Contact>
                      <gmd:onlineResource>
                        <gmd:CI_OnlineResource>
                          <gmd:linkage>
                            <gmd:URL>https://eumetsatspace.atlassian.net/wiki/spaces/SEN3/pages/1739096134/OLCI+How+can+I+retrieve+a+complete+archive+of+Sentinel-3+OLCI+data</gmd:URL>
                          </gmd:linkage>
                          <gmd:name>
                            <gco:CharacterString>FAQ: Retrieving OLCI time series</gco:CharacterString>
                          </gmd:name>
                          <gmd:function>
                            <gmd:CI_OnLineFunctionCode codeList="http://standards.iso.org/ittf/PubliclyAvailableStandards/ISO_19139_Schemas/resources/Codelist/gmxCodelists.xml#CI_OnLineFunctionCode" codeListValue="information"/>
                          </gmd:function>
                        </gmd:CI_OnlineResource>
                      </gmd:onlineResource>
                    </gmd:CI_Contact>
                  </gmd:contactInfo>
                  <gmd:role>
                    <gmd:CI_RoleCode codeList="http://standards.iso.org/ittf/PubliclyAvailableStandards/ISO_19139_Schemas/resources/Codelist/gmxCodelists.xml#CI_RoleCode" codeListValue="author"/>
                  </gmd:role>
                </gmd:CI_ResponsibleParty>
              </gmd:citedResponsibleParty>
              <gmd:citedResponsibleParty>
                <gmd:CI_ResponsibleParty>
                  <gmd:contactInfo>
                    <gmd:CI_Contact>
                      <gmd:onlineResource>
                        <gmd:CI_OnlineResource>
                          <gmd:linkage>
                            <gmd:URL>http://doi.org/10.15770/EUM_SEC_CLM_0062</gmd:URL>
                          </gmd:linkage>
                          <gmd:name>
                            <gco:CharacterString>OLCI Level 2 Ocean Colour Reduced Resolution (version BC003) - Sentinel-3 - Reprocessed</gco:CharacterString>
                          </gmd:name>
                          <gmd:function>
                            <gmd:CI_OnLineFunctionCode codeList="http://navigator.eumetsat.int/metadata_schema/eum/resources/Codelist/eum_gmxCodelists.xml#CI_OnLineFunctionCode" codeListValue="isPreviousVersionOf"/>
                          </gmd:function>
                        </gmd:CI_OnlineResource>
                      </gmd:onlineResource>
                    </gmd:CI_Contact>
                  </gmd:contactInfo>
                  <gmd:role>
                    <gmd:CI_RoleCode codeList="http://standards.iso.org/ittf/PubliclyAvailableStandards/ISO_19139_Schemas/resources/Codelist/gmxCodelists.xml#CI_RoleCode" codeListValue="author"/>
                  </gmd:role>
                </gmd:CI_ResponsibleParty>
              </gmd:citedResponsibleParty>
            </gmd:CI_Citation>
          </gmd:citation>
          <gmd:abstract>
            <gco:CharacterString>OLCI Level 2 Marine products provide spectral information on the colour of the oceans (water reflectances). These radiometric products are used to estimate geophysical parameters e.g. estimates of phytoplankton biomass through determining the Chlorophyll-a (Chl) concentration. In coastal areas, they also allow monitoring of the sediment load via the Total Suspended Matter (TSM) product. Reduced resolution products are at a nominal 1km resolution.

This collection contains reprocessed data from baseline collection 002. Operational data can be found in the corresponding collection.</gco:CharacterString>
          </gmd:abstract>
          <gmd:status>
            <gmd:MD_ProgressCode codeList="http://navigator.eumetsat.int/metadata_schema/eum/resources/Codelist/eum_gmxCodelists.xml#MD_ProgressCode" codeListValue="Released"/>
          </gmd:status>
          <gmd:pointOfContact>
            <gmd:CI_ResponsibleParty>
              <gmd:individualName>
                <gco:CharacterString>European Organisation for the Exploitation of Meteorological Satellites</gco:CharacterString>
              </gmd:individualName>
              <gmd:organisationName>
                <gco:CharacterString>EUMETSAT for Copernicus</gco:CharacterString>
              </gmd:organisationName>
              <gmd:contactInfo>
                <gmd:CI_Contact>
                  <gmd:phone>
                    <gmd:CI_Telephone>
                      <gmd:voice>
                        <gco:CharacterString>+49(0)6151-807 3660/3770</gco:CharacterString>
                      </gmd:voice>
                      <gmd:facsimile>
                        <gco:CharacterString>+49(0)6151-807 3790</gco:CharacterString>
                      </gmd:facsimile>
                    </gmd:CI_Telephone>
                  </gmd:phone>
                  <gmd:address>
                    <gmd:CI_Address>
                      <gmd:deliveryPoint>
                        <gco:CharacterString>EUMETSAT Allee 1</gco:CharacterString>
                      </gmd:deliveryPoint>
                      <gmd:city>
                        <gco:CharacterString>Darmstadt</gco:CharacterString>
                      </gmd:city>
                      <gmd:administrativeArea>
                        <gco:CharacterString>Hessen</gco:CharacterString>
                      </gmd:administrativeArea>
                      <gmd:postalCode>
                        <gco:CharacterString>64295</gco:CharacterString>
                      </gmd:postalCode>
                      <gmd:country>
                        <gco:CharacterString>Germany</gco:CharacterString>
                      </gmd:country>
                      <gmd:electronicMailAddress>
                        <gco:CharacterString>ops@eumetsat.int</gco:CharacterString>
                      </gmd:electronicMailAddress>
                    </gmd:CI_Address>
                  </gmd:address>
                  <gmd:onlineResource>
                    <gmd:CI_OnlineResource>
                      <gmd:linkage>
                        <gmd:URL>http://www.eumetsat.int</gmd:URL>
                      </gmd:linkage>
                    </gmd:CI_OnlineResource>
                  </gmd:onlineResource>
                </gmd:CI_Contact>
              </gmd:contactInfo>
              <gmd:role>
                <gmd:CI_RoleCode codeList="http://standards.iso.org/ittf/PubliclyAvailableStandards/ISO_19139_Schemas/resources/Codelist/ML_gmxCodelists.xml#MD_ScopeCode" codeListValue="originator">originator</gmd:CI_RoleCode>
              </gmd:role>
            </gmd:CI_ResponsibleParty>
          </gmd:pointOfContact>
          <gmd:graphicOverview>
            <gmd:MD_BrowseGraphic>
              <gmd:fileName>
                <gco:CharacterString>https://navigator.eumetsat.int/preview/WRR_BC003_x_large.png</gco:CharacterString>
              </gmd:fileName>
            </gmd:MD_BrowseGraphic>
          </gmd:graphicOverview>
          <gmd:descriptiveKeywords>
            <gmd:MD_Keywords>
              <gmd:keyword>
                <gco:CharacterString>Ocean</gco:CharacterString>
              </gmd:keyword>
              <gmd:keyword>
                <gco:CharacterString>Ocean Colour</gco:CharacterString>
              </gmd:keyword>
              <gmd:keyword>
                <gco:CharacterString>Radiation</gco:CharacterString>
              </gmd:keyword>
              <gmd:keyword>
                <gco:CharacterString>Level 2 Data</gco:CharacterString>
              </gmd:keyword>
              <gmd:type>
                <gmd:MD_KeywordTypeCode codeList="http://standards.iso.org/ittf/PubliclyAvailableStandards/ISO_19139_Schemas/resources/Codelist/gmxCodelists.xml#MD_KeywordTypeCode" codeListValue="theme"/>
              </gmd:type>
            </gmd:MD_Keywords>
          </gmd:descriptiveKeywords>
          <gmd:resourceConstraints>
            <gmd:MD_LegalConstraints>
              <gmd:useLimitation>
                <gco:CharacterString>-</gco:CharacterString>
              </gmd:useLimitation>
              <gmd:accessConstraints>
                <gmd:MD_RestrictionCode codeList="http://standards.iso.org/ittf/PubliclyAvailableStandards/ISO_19139_Schemas/resources/Codelist/gmxCodelists.xml#MD_RestrictionCode" codeListValue="copyright"/>
              </gmd:accessConstraints>
              <gmd:useConstraints>
                <gmd:MD_RestrictionCode codeList="http://standards.iso.org/ittf/PubliclyAvailableStandards/ISO_19139_Schemas/resources/Codelist/gmxCodelists.xml#MD_RestrictionCode" codeListValue="copyright"/>
              </gmd:useConstraints>
              <gmd:otherConstraints>
                <gmx:Anchor xlink:href="https://www.eumetsat.int/copernicus-data-usage-terms-and-conditions">Copernicus</gmx:Anchor>
              </gmd:otherConstraints>
            </gmd:MD_LegalConstraints>
          </gmd:resourceConstraints>
          <gmd:language>
            <gmd:LanguageCode codeList="http://www.w3.org/WAI/ER/IG/ert/iso639.htm" codeListValue="eng"/>
          </gmd:language>
          <gmd:characterSet>
            <gmd:MD_CharacterSetCode codeList="http://standards.iso.org/ittf/PubliclyAvailableStandards/ISO_19139_Schemas/resources/Codelist/gmxCodelists.xml#CI_CharacterSetCode" codeListValue="utf8"/>
          </gmd:characterSet>
          <gmd:topicCategory>
            <gmd:MD_TopicCategoryCode>climatologyMeteorologyAtmosphere</gmd:MD_TopicCategoryCode>
          </gmd:topicCategory>
          <gmd:extent>
            <gmd:EX_Extent>
              <gmd:temporalElement>
                <gmd:EX_TemporalExtent>
                  <gmd:extent>
                    <gml:TimePeriod gml:id="x1326aaa">
                      <gml:beginPosition>2016-04-25</gml:beginPosition>
                      <gml:endPosition>2017-11-29</gml:endPosition>
                    </gml:TimePeriod>
                  </gmd:extent>
                </gmd:EX_TemporalExtent>
              </gmd:temporalElement>
            </gmd:EX_Extent>
          </gmd:extent>
          <gmd:extent>
            <gmd:EX_Extent>
              <gmd:geographicElement>
                <gmd:EX_GeographicBoundingBox>
                  <gmd:extentTypeCode>
                    <gco:Boolean>true</gco:Boolean>
                  </gmd:extentTypeCode>
                  <gmd:westBoundLongitude>
                    <gco:Decimal>-180</gco:Decimal>
                  </gmd:westBoundLongitude>
                  <gmd:eastBoundLongitude>
                    <gco:Decimal>180</gco:Decimal>
                  </gmd:eastBoundLongitude>
                  <gmd:southBoundLatitude>
                    <gco:Decimal>-90</gco:Decimal>
                  </gmd:southBoundLatitude>
                  <gmd:northBoundLatitude>
                    <gco:Decimal>90</gco:Decimal>
                  </gmd:northBoundLatitude>
                </gmd:EX_GeographicBoundingBox>
              </gmd:geographicElement>
            </gmd:EX_Extent>
          </gmd:extent>
        </gmd:MD_DataIdentification>
      </gmd:identificationInfo>
      <gmd:contentInfo>
        <gmi:MI_CoverageDescription>
          <gmd:attributeDescription>
            <gco:RecordType>-</gco:RecordType>
          </gmd:attributeDescription>
          <gmd:contentType>
            <gmd:MD_CoverageContentTypeCode codeList="http://standards.iso.org/ittf/PubliclyAvailableStandards/ISO_19139_Schemas/resources/Codelist/gmxCodelists.xml#MD_CoverageContentTypeCode" codeListValue="image"/>
          </gmd:contentType>
        </gmi:MI_CoverageDescription>
      </gmd:contentInfo>
      <gmd:distributionInfo>
        <gmd:MD_Distribution>
          <gmd:distributor>
            <eum:MD_EUMDistributor>
              <gmd:distributorContact>
                <gmd:CI_ResponsibleParty>
                  <gmd:individualName>
                    <gco:CharacterString>European Organisation for the Exploitation of Meteorological Satellites</gco:CharacterString>
                  </gmd:individualName>
                  <gmd:organisationName>
                    <gco:CharacterString>EUMETSAT</gco:CharacterString>
                  </gmd:organisationName>
                  <gmd:contactInfo>
                    <gmd:CI_Contact>
                      <gmd:phone>
                        <gmd:CI_Telephone>
                          <gmd:voice>
                            <gco:CharacterString>+49(0)6151-807 3660/3770</gco:CharacterString>
                          </gmd:voice>
                          <gmd:facsimile>
                            <gco:CharacterString>+49(0)6151-807 3790</gco:CharacterString>
                          </gmd:facsimile>
                        </gmd:CI_Telephone>
                      </gmd:phone>
                      <gmd:address>
                        <gmd:CI_Address>
                          <gmd:deliveryPoint>
                            <gco:CharacterString>EUMETSAT Allee 1</gco:CharacterString>
                          </gmd:deliveryPoint>
                          <gmd:city>
                            <gco:CharacterString>Darmstadt</gco:CharacterString>
                          </gmd:city>
                          <gmd:administrativeArea>
                            <gco:CharacterString>Hessen</gco:CharacterString>
                          </gmd:administrativeArea>
                          <gmd:postalCode>
                            <gco:CharacterString>64295</gco:CharacterString>
                          </gmd:postalCode>
                          <gmd:country>
                            <gco:CharacterString>Germany</gco:CharacterString>
                          </gmd:country>
                          <gmd:electronicMailAddress>
                            <gco:CharacterString>ops@eumetsat.int</gco:CharacterString>
                          </gmd:electronicMailAddress>
                        </gmd:CI_Address>
                      </gmd:address>
                      <gmd:onlineResource>
                        <gmd:CI_OnlineResource>
                          <gmd:linkage>
                            <gmd:URL>http://www.eumetsat.int</gmd:URL>
                          </gmd:linkage>
                        </gmd:CI_OnlineResource>
                      </gmd:onlineResource>
                    </gmd:CI_Contact>
                  </gmd:contactInfo>
                  <gmd:role>
                    <gmd:CI_RoleCode codeList="http://standards.iso.org/ittf/PubliclyAvailableStandards/ISO_19139_Schemas/resources/Codelist/ML_gmxCodelists.xml#MD_ScopeCode" codeListValue="distributor">distributor</gmd:CI_RoleCode>
                  </gmd:role>
                </gmd:CI_ResponsibleParty>
              </gmd:distributorContact>
              <eum:digitalTransfers>
                <eum:MD_EUMDigitalTransfer>
                  <eum:availability>
                    <eum:MD_EUMDigitalTransferOptions>
                      <gmd:onLine>
                        <gmd:CI_OnlineResource>
                          <gmd:linkage>
                            <gmd:URL>https://data.eumetsat.int/data/map/EO:EUM:DAT:0593</gmd:URL>
                          </gmd:linkage>
                          <gmd:protocol>
                            <gco:CharacterString>https</gco:CharacterString>
                          </gmd:protocol>
                          <gmd:name>
                            <gco:CharacterString>Download</gco:CharacterString>
                          </gmd:name>
                          <gmd:function>
                            <gmd:CI_OnLineFunctionCode codeList="CI_OnLineFunctionCode" codeListValue="order"/>
                          </gmd:function>
                        </gmd:CI_OnlineResource>
                      </gmd:onLine>
                      <eum:availability>
                        <gco:CharacterString>Download</gco:CharacterString>
                      </eum:availability>
                    </eum:MD_EUMDigitalTransferOptions>
                  </eum:availability>
                  <eum:format>
                    <eum:MD_EUMFormat>
                      <gmd:name>
                        <gco:CharacterString>SENTINEL-SAFE</gco:CharacterString>
                      </gmd:name>
                      <gmd:version>
                        <gco:CharacterString>-</gco:CharacterString>
                      </gmd:version>
                      <eum:typicalFilename>
                        <gco:CharacterString>S3A_OL_2_WRR____20160425T113314_20160425T113436_20171029T130951_0082_003_237______MR1_R_NT_002.SEN3.zip</gco:CharacterString>
                      </eum:typicalFilename>
                      <eum:averageFileSizeUnits>
                        <gco:CharacterString>MB</gco:CharacterString>
                      </eum:averageFileSizeUnits>
                      <eum:averageFileSize>
                        <gco:Real>18</gco:Real>
                      </eum:averageFileSize>
                      <eum:frequency>
                        <gco:CharacterString>~323 (per day)</gco:CharacterString>
                      </eum:frequency>
                      <eum:fileFormatDescription>
                        <gco:CharacterString>The Sentinel-3 SAFE format wraps a folder containing a collection of measurement and annotation data in binary files (netCDF4 or raw binary based) and product metadata in XML. It is a Sentinel-3 specific variation of the Standard Archive Format for Europe (SAFE). This is sent in a compressed Submission Information Package (SIP).</gco:CharacterString>
                      </eum:fileFormatDescription>
                      <eum:documentation>
                        <CI_OnlineResource>
                          <linkage>
                            <URL>https://www.eumetsat.int/formats#netCDF</URL>
                          </linkage>
                          <description>
                            <gco:CharacterString>netCDF documentation and tools</gco:CharacterString>
                          </description>
                        </CI_OnlineResource>
                      </eum:documentation>
                      <eum:documentation>
                        <CI_OnlineResource>
                          <linkage>
                            <URL>https://www.eumetsat.int/formats#SIP</URL>
                          </linkage>
                          <description>
                            <gco:CharacterString>SIP documentation and tools</gco:CharacterString>
                          </description>
                        </CI_OnlineResource>
                      </eum:documentation>
                      <eum:documentation>
                        <CI_OnlineResource>
                          <linkage>
                            <URL>https://www.eumetsat.int/formats#SENTINEL-SAFE</URL>
                          </linkage>
                          <description>
                            <gco:CharacterString>SENTINEL-SAFE documentation and tools</gco:CharacterString>
                          </description>
                        </CI_OnlineResource>
                      </eum:documentation>
                      <eum:totalSizeOfDatasetUnits>
                        <gco:CharacterString>TB</gco:CharacterString>
                      </eum:totalSizeOfDatasetUnits>
                      <eum:totalSizeOfDataset>
                        <gco:Real>3.3</gco:Real>
                      </eum:totalSizeOfDataset>
                      <eum:format4DataCite>
                        <gco:Boolean>true</gco:Boolean>
                      </eum:format4DataCite>
                    </eum:MD_EUMFormat>
                  </eum:format>
                </eum:MD_EUMDigitalTransfer>
              </eum:digitalTransfers>
            </eum:MD_EUMDistributor>
          </gmd:distributor>
        </gmd:MD_Distribution>
      </gmd:distributionInfo>
      <gmd:dataQualityInfo>
        <gmd:DQ_DataQuality>
          <gmd:scope>
            <gmd:DQ_Scope>
              <gmd:level>
                <gmd:MD_ScopeCode codeList="http://standards.iso.org/ittf/PubliclyAvailableStandards/ISO_19139_Schemas/resources/codelist/gmxCodelists.xml#MD_ScopeCode" codeListValue="series"/>
              </gmd:level>
            </gmd:DQ_Scope>
          </gmd:scope>
          <gmd:lineage>
            <gmd:LI_Lineage>
              <gmd:statement>
                <gco:CharacterString>-</gco:CharacterString>
              </gmd:statement>
            </gmd:LI_Lineage>
          </gmd:lineage>
        </gmd:DQ_DataQuality>
      </gmd:dataQualityInfo>
      <gmi:acquisitionInformation>
        <gmi:MI_AcquisitionInformation>
          <gmi:platform>
            <eum:MI_EUMPlatform>
              <gmi:identifier>
                <gmd:MD_Identifier>
                  <gmd:code>
                    <gco:CharacterString>Sentinel-3</gco:CharacterString>
                  </gmd:code>
                </gmd:MD_Identifier>
              </gmi:identifier>
              <gmi:description>
                <gco:CharacterString>Sentinel-3</gco:CharacterString>
              </gmi:description>
              <gmi:instrument>
                <eum:MI_EUMInstrument>
                  <gmi:citation>
                    <gmd:CI_Citation>
                      <gmd:title>
                        <gco:CharacterString>OLCI</gco:CharacterString>
                      </gmd:title>
                      <gmd:date>
                        <gmd:CI_Date>
                          <gmd:date>
                            <gco:Date>2008-06-01</gco:Date>
                          </gmd:date>
                          <gmd:dateType>
                            <gmd:CI_DateTypeCode codeList="http://standards.iso.org/ittf/PubliclyAvailableStandards/ISO_19139_Schemas/resources/Codelist/gmxCodelists.xml#CI_DateTypeCode" codeListValue="creation"/>
                          </gmd:dateType>
                        </gmd:CI_Date>
                      </gmd:date>
                      <gmd:identifier>
                        <gmd:MD_Identifier>
                          <gmd:code>
                            <gco:CharacterString>OLCI</gco:CharacterString>
                          </gmd:code>
                        </gmd:MD_Identifier>
                      </gmd:identifier>
                    </gmd:CI_Citation>
                  </gmi:citation>
                  <gmi:type>
                    <gmi:MI_SensorTypeCode id="z615aaa" uuid="z615aaa"/>
                  </gmi:type>
                  <eum:type>
                    <MI_EUMSensorTypeCode xmlns="http://www.eumetsat.int/2008/gmi" codeList="http://navigator.eumetsat.int/metadata_schema/eum/resources/Codelist/eum_gmxCodelists.xml#CI_SensorTypeCode" codeListValue="Optical"/>
                  </eum:type>
                </eum:MI_EUMInstrument>
              </gmi:instrument>
              <eum:orbitType>
                <CI_OrbitTypeCode xmlns="http://www.eumetsat.int/2008/gmi" codeList="http://standards.iso.org/ittf/PubliclyAvailableStandards/ISO_19139_Schemas/resources/Codelist/gmxCodelists.xml#CI_OrbitTypeCode" codeListValue="LEO"/>
              </eum:orbitType>
            </eum:MI_EUMPlatform>
          </gmi:platform>
        </gmi:MI_AcquisitionInformation>
      </gmi:acquisitionInformation>
    </gmi:MI_Metadata>
    